codejson_index_generator/__init__.py
codejson_index_generator/parsers.py
codejson_index_generator-1.1.0.dist-info/LICENSE
codejson_index_generator-1.1.0.dist-info/METADATA
codejson_index_generator-1.1.0.dist-info/WHEEL
codejson_index_generator-1.1.0.dist-info/RECORD
