Metadata-Version: 2.3
Name: codejson-index-generator
Version: 1.1.0
Summary: Script to create an indexed code.json for agencies.
License: CC0-1.0
Author: Sachin Panayil
Author-email: sachinpanayil01@gmail.com
Requires-Python: >=3.13,<4.0
Classifier: License :: CC0 1.0 Universal (CC0 1.0) Public Domain Dedication
Classifier: Programming Language :: Python :: 3
Classifier: Programming Language :: Python :: 3.13
Requires-Dist: pygithub (>=1.59,<2.0)
Project-URL: Repository, https://github.com/DSACMS/codejson-index-generator
